{"version":1,"resource":"file:///home/arts/aurGit/learningC/firstMessOfStuff.c","entries":[{"id":"gAjE.c","timestamp":1735053859678},{"id":"WljD.c","timestamp":1735078433636},{"id":"XZka.c","timestamp":1735218308356},{"id":"ah4P.c","timestamp":1735218328956},{"id":"XU8T.c","timestamp":1735218510274},{"id":"Ozxu.c","timestamp":1735218762515},{"id":"QqNB.c","timestamp":1735224069524},{"id":"ytdL.c","timestamp":1735224145561},{"id":"6F7J.c","timestamp":1735224162514},{"id":"AXRN.c","timestamp":1735231078669},{"id":"4MOd.c","timestamp":1735265295293},{"id":"rpHm.c","timestamp":1735265415208},{"id":"U5Ak.c","timestamp":1735265426663},{"id":"59kV.c","timestamp":1735266704169},{"id":"g21g.c","timestamp":1735266769264},{"id":"emC2.c","timestamp":1735266779577},{"id":"fu5s.c","timestamp":1735266800626},{"id":"NgNx.c","timestamp":1735266891457},{"id":"xK2e.c","timestamp":1735266920559},{"id":"jUUQ.c","timestamp":1735266991450},{"id":"Y1zi.c","timestamp":1735267520869},{"id":"YIlu.c","timestamp":1735267550887},{"id":"jMRk.c","source":"undoRedo.source","timestamp":1735267597194},{"id":"deVT.c","timestamp":1735267803591},{"id":"vOsy.c","timestamp":1735267876501},{"id":"VEfh.c","timestamp":1735267904178},{"id":"6MzG.c","timestamp":1735267949897},{"id":"jqrk.c","timestamp":1735267972674},{"id":"ph1z.c","timestamp":1735268001033},{"id":"jYgq.c","timestamp":1735268068743},{"id":"x3EJ.c","timestamp":1735268238044},{"id":"fsjz.c","timestamp":1735268261543},{"id":"OtPl.c","timestamp":1735268298362},{"id":"TFSd.c","timestamp":1735268322102},{"id":"HH6i.c","timestamp":1735268372381},{"id":"OXl0.c","timestamp":1735268388337},{"id":"LxzG.c","timestamp":1741007580956},{"id":"zKaV.c","timestamp":1741007603030},{"id":"WAlD.c","timestamp":1741007621190},{"id":"ajBu.c","timestamp":1741007659877},{"id":"KYPF.c","timestamp":1741007723314},{"id":"NUTR.c","timestamp":1741008022065},{"id":"hfhi.c","timestamp":1741008517967},{"id":"goqh.c","timestamp":1741008605081},{"id":"GLNP.c","timestamp":1741008615681},{"id":"aMyw.c","timestamp":1741008634994},{"id":"S1T1.c","timestamp":1741008667491},{"id":"aSyc.c","timestamp":1741008687774},{"id":"notq.c","timestamp":1741008772084},{"id":"tb5V.c","timestamp":1741008812531}]}